MANIFEST.in
README.md
setup.py
pdtweak/__init__.py
pdtweak/memorysaver.py
pdtweak.egg-info/PKG-INFO
pdtweak.egg-info/SOURCES.txt
pdtweak.egg-info/dependency_links.txt
pdtweak.egg-info/not-zip-safe
pdtweak.egg-info/requires.txt
pdtweak.egg-info/top_level.txt