Metadata-Version: 2.1
Name: pdtweak
Version: 0.1.0
Summary: pandas utility functions
Home-page: http://github.com/kmedian/pdtweak
Author: Ulf Hamster
Author-email: 554c46@gmail.com
License: MIT
Platform: UNKNOWN
Requires-Python: >=3.6
